control_utils/__init__.py
control_utils-1.0.5.dist-info/METADATA
control_utils-1.0.5.dist-info/WHEEL
control_utils-1.0.5.dist-info/top_level.txt
control_utils-1.0.5.dist-info/RECORD
