Metadata-Version: 2.1
Name: control-utils
Version: 1.0.5
Summary: package for helping with teaching or learning feedback control
Home-page: https://github.com/ryanGT/control_utils
Author: Ryan Krauss
Author-email: ryanwkrauss@gmail.com
License: UNKNOWN
Platform: UNKNOWN
Classifier: Programming Language :: Python :: 3
Classifier: License :: OSI Approved :: MIT License
Classifier: Operating System :: OS Independent
